{
	"$schema": "http://schema.management.azure.com/schemas/2015-01-01/deploymentTemplate.json#",
	"contentVersion": "1.0.0.0",
	"parameters": {
		"factoryName": {
			"type": "string",
			"metadata": "Data Factory name",
			"defaultValue": "adfmigration009"
		},
		"DS_SQLSERVER_TABLE_password": {
			"type": "secureString",
			"metadata": "Secure string for 'password' of 'DS_SQLSERVER_TABLE'"
		},
		"LS_ADLS_CP_FILTER_accountKey": {
			"type": "secureString",
			"metadata": "Secure string for 'accountKey' of 'LS_ADLS_CP_FILTER'"
		},
		"LS_ADLS_CSV_accountKey": {
			"type": "secureString",
			"metadata": "Secure string for 'accountKey' of 'LS_ADLS_CSV'"
		},
		"LS_ADLS_FILES_accountKey": {
			"type": "secureString",
			"metadata": "Secure string for 'accountKey' of 'LS_ADLS_FILES'"
		},
		"LS_ADLS_PARQUET_accountKey": {
			"type": "secureString",
			"metadata": "Secure string for 'accountKey' of 'LS_ADLS_PARQUET'"
		},
		"LS_CP_SQL_FULL_password": {
			"type": "secureString",
			"metadata": "Secure string for 'password' of 'LS_CP_SQL_FULL'"
		},
		"LS_ONPREM_SQLSERVER_DW_password": {
			"type": "secureString",
			"metadata": "Secure string for 'password' of 'LS_ONPREM_SQLSERVER_DW'"
		},
		"LS_SQLSERVER_password": {
			"type": "secureString",
			"metadata": "Secure string for 'password' of 'LS_SQLSERVER'"
		},
		"LS_SQLSERVER_TABLE_password": {
			"type": "secureString",
			"metadata": "Secure string for 'password' of 'LS_SQLSERVER_TABLE'"
		},
		"LS_SQLSER_TABLE_password": {
			"type": "secureString",
			"metadata": "Secure string for 'password' of 'LS_SQLSER_TABLE'"
		},
		"LS_parquet_accountKey": {
			"type": "secureString",
			"metadata": "Secure string for 'accountKey' of 'LS_parquet'"
		},
		"DS_SQLSERVER_TABLE_properties_typeProperties_server": {
			"type": "string",
			"defaultValue": "DESKTOP-SPFUOTO"
		},
		"DS_SQLSERVER_TABLE_properties_typeProperties_database": {
			"type": "string",
			"defaultValue": "tables"
		},
		"DS_SQLSERVER_TABLE_properties_typeProperties_userName": {
			"type": "string",
			"defaultValue": "monark"
		},
		"LS_ADLS_CP_FILTER_properties_typeProperties_url": {
			"type": "string",
			"defaultValue": "https://adlsmigration009.dfs.core.windows.net/"
		},
		"LS_ADLS_CSV_properties_typeProperties_url": {
			"type": "string",
			"defaultValue": "https://adlsmigration009.dfs.core.windows.net/"
		},
		"LS_ADLS_FILES_properties_typeProperties_url": {
			"type": "string",
			"defaultValue": "https://adlsmigration009.dfs.core.windows.net/"
		},
		"LS_ADLS_PARQUET_properties_typeProperties_url": {
			"type": "string",
			"defaultValue": "https://adlsmigration009.dfs.core.windows.net/"
		},
		"LS_CP_SQL_FULL_properties_typeProperties_server": {
			"type": "string",
			"defaultValue": "DESKTOP-SPFUOTO"
		},
		"LS_CP_SQL_FULL_properties_typeProperties_database": {
			"type": "string",
			"defaultValue": "tables"
		},
		"LS_CP_SQL_FULL_properties_typeProperties_userName": {
			"type": "string",
			"defaultValue": "monark"
		},
		"LS_ONPREM_SQLSERVER_DW_properties_typeProperties_server": {
			"type": "string",
			"defaultValue": "DESKTOP-SPFUOTO"
		},
		"LS_ONPREM_SQLSERVER_DW_properties_typeProperties_database": {
			"type": "string",
			"defaultValue": "tables"
		},
		"LS_ONPREM_SQLSERVER_DW_properties_typeProperties_userName": {
			"type": "string",
			"defaultValue": "monark"
		},
		"LS_SQLSERVER_properties_typeProperties_server": {
			"type": "string",
			"defaultValue": "DESKTOP-SPFUOTO"
		},
		"LS_SQLSERVER_properties_typeProperties_database": {
			"type": "string",
			"defaultValue": "tables"
		},
		"LS_SQLSERVER_properties_typeProperties_userName": {
			"type": "string",
			"defaultValue": "monark"
		},
		"LS_SQLSERVER_TABLE_properties_typeProperties_server": {
			"type": "string",
			"defaultValue": "DESKTOP-SPFUOTO"
		},
		"LS_SQLSERVER_TABLE_properties_typeProperties_database": {
			"type": "string",
			"defaultValue": "tables"
		},
		"LS_SQLSERVER_TABLE_properties_typeProperties_userName": {
			"type": "string",
			"defaultValue": "monark"
		},
		"LS_SQLSER_TABLE_properties_typeProperties_server": {
			"type": "string",
			"defaultValue": "DESKTOP-SPFUOTO"
		},
		"LS_SQLSER_TABLE_properties_typeProperties_database": {
			"type": "string",
			"defaultValue": "tables"
		},
		"LS_SQLSER_TABLE_properties_typeProperties_userName": {
			"type": "string",
			"defaultValue": "monark"
		},
		"LS_parquet_properties_typeProperties_url": {
			"type": "string",
			"defaultValue": "https://adlsmigration009.dfs.core.windows.net/"
		}
	},
	"variables": {
		"factoryId": "[concat('Microsoft.DataFactory/factories/', parameters('factoryName'))]"
	},
	"resources": [
		{
			"name": "[concat(parameters('factoryName'), '/PL_CHILD_SP_UPDTWM')]",
			"type": "Microsoft.DataFactory/factories/pipelines",
			"apiVersion": "2018-06-01",
			"properties": {
				"activities": [
					{
						"name": "SP_UPDT_WATERMARK",
						"type": "SqlServerStoredProcedure",
						"dependsOn": [],
						"policy": {
							"timeout": "0.12:00:00",
							"retry": 0,
							"retryIntervalInSeconds": 30,
							"secureOutput": false,
							"secureInput": false
						},
						"userProperties": [],
						"typeProperties": {
							"storedProcedureName": "[[dbo].[UpdateWatermark]",
							"storedProcedureParameters": {
								"TableName": {
									"value": {
										"value": "@pipeline().parameters.TableName",
										"type": "Expression"
									}
								},
								"TableSchema": {
									"value": {
										"value": "@pipeline().parameters.TableSchema",
										"type": "Expression"
									}
								},
								"WatermarkColumn": {
									"value": {
										"value": "@pipeline().parameters.WatermarkColumn",
										"type": "Expression"
									}
								}
							}
						},
						"linkedServiceName": {
							"referenceName": "LS_ONPREM_SQLSERVER_DW",
							"type": "LinkedServiceReference"
						}
					}
				],
				"policy": {
					"elapsedTimeMetric": {}
				},
				"parameters": {
					"TableSchema": {
						"type": "string"
					},
					"TableName": {
						"type": "string"
					},
					"WatermarkColumn": {
						"type": "string"
					}
				},
				"annotations": [],
				"lastPublishTime": "2026-03-25T12:33:12Z"
			},
			"dependsOn": [
				"[concat(variables('factoryId'), '/linkedServices/LS_ONPREM_SQLSERVER_DW')]"
			]
		},
		{
			"name": "[concat(parameters('factoryName'), '/PL_CHILED_INCRE')]",
			"type": "Microsoft.DataFactory/factories/pipelines",
			"apiVersion": "2018-06-01",
			"properties": {
				"activities": [
					{
						"name": "LKUP_WATERMARK_OP",
						"type": "Lookup",
						"dependsOn": [],
						"policy": {
							"timeout": "0.12:00:00",
							"retry": 0,
							"retryIntervalInSeconds": 30,
							"secureOutput": false,
							"secureInput": false
						},
						"userProperties": [],
						"typeProperties": {
							"source": {
								"type": "SqlServerSource",
								"sqlReaderQuery": {
									"value": "SELECT MAX(@{pipeline().parameters.WatermarkColumn}) AS MaxValue\nFROM @{pipeline().parameters.TableSchema}.@{pipeline().parameters.TableName}\n\n",
									"type": "Expression"
								},
								"queryTimeout": "02:00:00",
								"partitionOption": "None"
							},
							"dataset": {
								"referenceName": "DS_SQLSERVER_TABLE",
								"type": "DatasetReference",
								"parameters": {}
							},
							"firstRowOnly": false
						}
					},
					{
						"name": "IF_NEWRECORD_EXIST",
						"type": "IfCondition",
						"dependsOn": [
							{
								"activity": "LKUP_WATERMARK_OP",
								"dependencyConditions": [
									"Succeeded"
								]
							}
						],
						"userProperties": [],
						"typeProperties": {
							"expression": {
								"value": "@or(\n    equals(pipeline().parameters.LastLoadValue, null), \n    greater(\n        int(activity('LKUP_WATERMARK_OP').output.value[0].MaxValue), \n        int(pipeline().parameters.LastLoadValue)\n        )\n    )",
								"type": "Expression"
							},
							"ifTrueActivities": [
								{
									"name": "CP_SQL_FULL",
									"type": "Copy",
									"dependsOn": [],
									"policy": {
										"timeout": "0.12:00:00",
										"retry": 0,
										"retryIntervalInSeconds": 30,
										"secureOutput": false,
										"secureInput": false
									},
									"userProperties": [],
									"typeProperties": {
										"source": {
											"type": "SqlServerSource",
											"sqlReaderQuery": {
												"value": "@concat(\n    'SELECT * FROM ',\n    pipeline().parameters.TableSchema, '.', pipeline().parameters.TableName,\n    if(\n        equals(pipeline().parameters.LastLoadValue, null),\n        '', \n        concat(\n            ' WHERE ', pipeline().parameters.WatermarkColumn,\n            ' > ''', pipeline().parameters.LastLoadValue, ''''\n        )\n    )\n)",
												"type": "Expression"
											},
											"queryTimeout": "02:00:00",
											"partitionOption": "None"
										},
										"sink": {
											"type": "ParquetSink",
											"storeSettings": {
												"type": "AzureBlobFSWriteSettings"
											},
											"formatSettings": {
												"type": "ParquetWriteSettings"
											}
										},
										"enableStaging": false,
										"translator": {
											"type": "TabularTranslator",
											"typeConversion": true,
											"typeConversionSettings": {
												"allowDataTruncation": true,
												"treatBooleanAsNumber": false
											}
										}
									},
									"inputs": [
										{
											"referenceName": "DS_CP_SQL_FULL",
											"type": "DatasetReference",
											"parameters": {
												"SchemaName": {
													"value": "@pipeline().parameters.TableSchema",
													"type": "Expression"
												},
												"TableName": {
													"value": "@pipeline().parameters.TableName",
													"type": "Expression"
												}
											}
										}
									],
									"outputs": [
										{
											"referenceName": "DS_ADLS_PARQUET",
											"type": "DatasetReference",
											"parameters": {
												"Table_Name": {
													"value": "@pipeline().parameters.TableName",
													"type": "Expression"
												}
											}
										}
									]
								},
								{
									"name": "EXEC_CHILD_INCRE",
									"type": "ExecutePipeline",
									"dependsOn": [
										{
											"activity": "CP_SQL_FULL",
											"dependencyConditions": [
												"Succeeded"
											]
										}
									],
									"policy": {
										"secureInput": false
									},
									"userProperties": [],
									"typeProperties": {
										"pipeline": {
											"referenceName": "PL_CHILD_SP_UPDTWM",
											"type": "PipelineReference"
										},
										"waitOnCompletion": true,
										"parameters": {
											"TableSchema": {
												"value": "@pipeline().parameters.TableSchema",
												"type": "Expression"
											},
											"TableName": {
												"value": "@pipeline().parameters.TableName",
												"type": "Expression"
											},
											"WatermarkColumn": {
												"value": "@pipeline().parameters.WatermarkColumn",
												"type": "Expression"
											}
										}
									}
								}
							]
						}
					}
				],
				"policy": {
					"elapsedTimeMetric": {}
				},
				"parameters": {
					"TableName": {
						"type": "string"
					},
					"WatermarkColumn": {
						"type": "string"
					},
					"TableSchema": {
						"type": "string"
					},
					"LastLoadValue": {
						"type": "string"
					}
				},
				"annotations": [],
				"lastPublishTime": "2026-03-25T12:36:56Z"
			},
			"dependsOn": [
				"[concat(variables('factoryId'), '/datasets/DS_SQLSERVER_TABLE')]",
				"[concat(variables('factoryId'), '/datasets/DS_CP_SQL_FULL')]",
				"[concat(variables('factoryId'), '/datasets/DS_ADLS_PARQUET')]",
				"[concat(variables('factoryId'), '/pipelines/PL_CHILD_SP_UPDTWM')]"
			]
		},
		{
			"name": "[concat(parameters('factoryName'), '/PL_PARENT_ORECHE')]",
			"type": "Microsoft.DataFactory/factories/pipelines",
			"apiVersion": "2018-06-01",
			"properties": {
				"activities": [
					{
						"name": "LKUP_SQLSERVER",
						"type": "Lookup",
						"dependsOn": [],
						"policy": {
							"timeout": "0.12:00:00",
							"retry": 0,
							"retryIntervalInSeconds": 30,
							"secureOutput": false,
							"secureInput": false
						},
						"userProperties": [],
						"typeProperties": {
							"source": {
								"type": "SqlServerSource",
								"sqlReaderQuery": {
									"value": "SELECT TableSchema, TableName, WatermarkColumn, LastLoadValue\nFROM dbo.ADF_Watermark_Table;",
									"type": "Expression"
								},
								"queryTimeout": "02:00:00",
								"partitionOption": "None"
							},
							"dataset": {
								"referenceName": "DS_SQLSERVER",
								"type": "DatasetReference",
								"parameters": {}
							},
							"firstRowOnly": false
						}
					},
					{
						"name": "FOR_SQLSERVER_WATMAR",
						"type": "ForEach",
						"dependsOn": [
							{
								"activity": "LKUP_SQLSERVER",
								"dependencyConditions": [
									"Succeeded"
								]
							}
						],
						"userProperties": [],
						"typeProperties": {
							"items": {
								"value": "@activity('LKUP_SQLSERVER').output.value",
								"type": "Expression"
							},
							"isSequential": false,
							"activities": [
								{
									"name": "EXEC_SQLSERVER_WATMARK",
									"type": "ExecutePipeline",
									"dependsOn": [],
									"policy": {
										"secureInput": false
									},
									"userProperties": [],
									"typeProperties": {
										"pipeline": {
											"referenceName": "PL_CHILED_INCRE",
											"type": "PipelineReference"
										},
										"waitOnCompletion": true,
										"parameters": {
											"TableName": {
												"value": "@item().TableName",
												"type": "Expression"
											},
											"WatermarkColumn": {
												"value": "@item().WatermarkColumn",
												"type": "Expression"
											},
											"TableSchema": {
												"value": "@item().TableSchema",
												"type": "Expression"
											},
											"LastLoadValue": {
												"value": "@item().LastLoadValue",
												"type": "Expression"
											}
										}
									}
								}
							]
						}
					}
				],
				"policy": {
					"elapsedTimeMetric": {}
				},
				"annotations": [],
				"lastPublishTime": "2026-03-25T12:33:12Z"
			},
			"dependsOn": [
				"[concat(variables('factoryId'), '/datasets/DS_SQLSERVER')]",
				"[concat(variables('factoryId'), '/pipelines/PL_CHILED_INCRE')]"
			]
		},
		{
			"name": "[concat(parameters('factoryName'), '/DS_ADLS_PARQUET')]",
			"type": "Microsoft.DataFactory/factories/datasets",
			"apiVersion": "2018-06-01",
			"properties": {
				"linkedServiceName": {
					"referenceName": "LS_ADLS_PARQUET",
					"type": "LinkedServiceReference"
				},
				"parameters": {
					"Table_Name": {
						"type": "string"
					}
				},
				"annotations": [],
				"type": "Parquet",
				"typeProperties": {
					"location": {
						"type": "AzureBlobFSLocation",
						"fileName": {
							"value": "@concat(dataset().Table_Name,'_',formatDateTime(utcNow(),'yyyyMMddHHmmss'),'.parquet')",
							"type": "Expression"
						},
						"folderPath": {
							"value": "@concat(dataset().Table_Name,'/',formatDateTime(utcNow(),'yyyy/MM/dd'))",
							"type": "Expression"
						},
						"fileSystem": "retaildeparquet"
					},
					"compressionCodec": "snappy"
				},
				"schema": []
			},
			"dependsOn": [
				"[concat(variables('factoryId'), '/linkedServices/LS_ADLS_PARQUET')]"
			]
		},
		{
			"name": "[concat(parameters('factoryName'), '/DS_CP_SQL_FULL')]",
			"type": "Microsoft.DataFactory/factories/datasets",
			"apiVersion": "2018-06-01",
			"properties": {
				"linkedServiceName": {
					"referenceName": "LS_CP_SQL_FULL",
					"type": "LinkedServiceReference"
				},
				"parameters": {
					"SchemaName": {
						"type": "string"
					},
					"TableName": {
						"type": "string"
					}
				},
				"annotations": [],
				"type": "SqlServerTable",
				"schema": [],
				"typeProperties": {
					"schema": {
						"value": "@dataset().SchemaName",
						"type": "Expression"
					},
					"table": {
						"value": "@dataset().TableName",
						"type": "Expression"
					}
				}
			},
			"dependsOn": [
				"[concat(variables('factoryId'), '/linkedServices/LS_CP_SQL_FULL')]"
			]
		},
		{
			"name": "[concat(parameters('factoryName'), '/DS_SQLSERVER')]",
			"type": "Microsoft.DataFactory/factories/datasets",
			"apiVersion": "2018-06-01",
			"properties": {
				"linkedServiceName": {
					"referenceName": "LS_SQLSERVER",
					"type": "LinkedServiceReference"
				},
				"annotations": [],
				"type": "SqlServerTable",
				"schema": [
					{
						"name": "TableSchema",
						"type": "varchar"
					},
					{
						"name": "TableName",
						"type": "varchar"
					},
					{
						"name": "WatermarkColumn",
						"type": "varchar"
					},
					{
						"name": "LastLoadValue",
						"type": "bigint",
						"precision": 19
					}
				],
				"typeProperties": {
					"schema": "dbo",
					"table": "ADF_Watermark_Table"
				}
			},
			"dependsOn": [
				"[concat(variables('factoryId'), '/linkedServices/LS_SQLSERVER')]"
			]
		},
		{
			"name": "[concat(parameters('factoryName'), '/DS_SQLSERVER_TABLE')]",
			"type": "Microsoft.DataFactory/factories/datasets",
			"apiVersion": "2018-06-01",
			"properties": {
				"linkedServiceName": {
					"referenceName": "LS_SQLSERVER_TABLE",
					"type": "LinkedServiceReference"
				},
				"annotations": [],
				"type": "SqlServerTable",
				"schema": [
					{
						"name": "TableSchema",
						"type": "varchar"
					},
					{
						"name": "TableName",
						"type": "varchar"
					},
					{
						"name": "WatermarkColumn",
						"type": "varchar"
					},
					{
						"name": "LastLoadValue",
						"type": "bigint",
						"precision": 19
					}
				],
				"typeProperties": {
					"schema": "dbo",
					"table": "ADF_Watermark_Table"
				}
			},
			"dependsOn": [
				"[concat(variables('factoryId'), '/linkedServices/LS_SQLSERVER_TABLE')]"
			]
		},
		{
			"name": "[concat(parameters('factoryName'), '/DS_SQLSERVER_TABLE')]",
			"type": "Microsoft.DataFactory/factories/linkedServices",
			"apiVersion": "2018-06-01",
			"properties": {
				"annotations": [],
				"type": "SqlServer",
				"typeProperties": {
					"server": "[parameters('DS_SQLSERVER_TABLE_properties_typeProperties_server')]",
					"database": "[parameters('DS_SQLSERVER_TABLE_properties_typeProperties_database')]",
					"encrypt": "optional",
					"trustServerCertificate": false,
					"authenticationType": "SQL",
					"userName": "[parameters('DS_SQLSERVER_TABLE_properties_typeProperties_userName')]",
					"password": {
						"type": "SecureString",
						"value": "[parameters('DS_SQLSERVER_TABLE_password')]"
					}
				},
				"connectVia": {
					"referenceName": "integrationRuntime1",
					"type": "IntegrationRuntimeReference"
				}
			},
			"dependsOn": [
				"[concat(variables('factoryId'), '/integrationRuntimes/integrationRuntime1')]"
			]
		},
		{
			"name": "[concat(parameters('factoryName'), '/LS_ADLS_CP_FILTER')]",
			"type": "Microsoft.DataFactory/factories/linkedServices",
			"apiVersion": "2018-06-01",
			"properties": {
				"annotations": [],
				"type": "AzureBlobFS",
				"typeProperties": {
					"url": "[parameters('LS_ADLS_CP_FILTER_properties_typeProperties_url')]",
					"accountKey": {
						"type": "SecureString",
						"value": "[parameters('LS_ADLS_CP_FILTER_accountKey')]"
					}
				}
			},
			"dependsOn": []
		},
		{
			"name": "[concat(parameters('factoryName'), '/LS_ADLS_CSV')]",
			"type": "Microsoft.DataFactory/factories/linkedServices",
			"apiVersion": "2018-06-01",
			"properties": {
				"annotations": [],
				"type": "AzureBlobFS",
				"typeProperties": {
					"url": "[parameters('LS_ADLS_CSV_properties_typeProperties_url')]",
					"accountKey": {
						"type": "SecureString",
						"value": "[parameters('LS_ADLS_CSV_accountKey')]"
					}
				}
			},
			"dependsOn": []
		},
		{
			"name": "[concat(parameters('factoryName'), '/LS_ADLS_FILES')]",
			"type": "Microsoft.DataFactory/factories/linkedServices",
			"apiVersion": "2018-06-01",
			"properties": {
				"annotations": [],
				"type": "AzureBlobFS",
				"typeProperties": {
					"url": "[parameters('LS_ADLS_FILES_properties_typeProperties_url')]",
					"accountKey": {
						"type": "SecureString",
						"value": "[parameters('LS_ADLS_FILES_accountKey')]"
					}
				}
			},
			"dependsOn": []
		},
		{
			"name": "[concat(parameters('factoryName'), '/LS_ADLS_PARQUET')]",
			"type": "Microsoft.DataFactory/factories/linkedServices",
			"apiVersion": "2018-06-01",
			"properties": {
				"annotations": [],
				"type": "AzureBlobFS",
				"typeProperties": {
					"url": "[parameters('LS_ADLS_PARQUET_properties_typeProperties_url')]",
					"accountKey": {
						"type": "SecureString",
						"value": "[parameters('LS_ADLS_PARQUET_accountKey')]"
					}
				}
			},
			"dependsOn": []
		},
		{
			"name": "[concat(parameters('factoryName'), '/LS_CP_SQL_FULL')]",
			"type": "Microsoft.DataFactory/factories/linkedServices",
			"apiVersion": "2018-06-01",
			"properties": {
				"annotations": [],
				"type": "SqlServer",
				"typeProperties": {
					"server": "[parameters('LS_CP_SQL_FULL_properties_typeProperties_server')]",
					"database": "[parameters('LS_CP_SQL_FULL_properties_typeProperties_database')]",
					"encrypt": "optional",
					"trustServerCertificate": false,
					"authenticationType": "SQL",
					"userName": "[parameters('LS_CP_SQL_FULL_properties_typeProperties_userName')]",
					"password": {
						"type": "SecureString",
						"value": "[parameters('LS_CP_SQL_FULL_password')]"
					}
				},
				"connectVia": {
					"referenceName": "integrationRuntime1",
					"type": "IntegrationRuntimeReference"
				}
			},
			"dependsOn": [
				"[concat(variables('factoryId'), '/integrationRuntimes/integrationRuntime1')]"
			]
		},
		{
			"name": "[concat(parameters('factoryName'), '/LS_ONPREM_SQLSERVER_DW')]",
			"type": "Microsoft.DataFactory/factories/linkedServices",
			"apiVersion": "2018-06-01",
			"properties": {
				"annotations": [],
				"type": "SqlServer",
				"typeProperties": {
					"server": "[parameters('LS_ONPREM_SQLSERVER_DW_properties_typeProperties_server')]",
					"database": "[parameters('LS_ONPREM_SQLSERVER_DW_properties_typeProperties_database')]",
					"encrypt": "optional",
					"trustServerCertificate": false,
					"authenticationType": "SQL",
					"userName": "[parameters('LS_ONPREM_SQLSERVER_DW_properties_typeProperties_userName')]",
					"password": {
						"type": "SecureString",
						"value": "[parameters('LS_ONPREM_SQLSERVER_DW_password')]"
					}
				},
				"connectVia": {
					"referenceName": "integrationRuntime1",
					"type": "IntegrationRuntimeReference"
				}
			},
			"dependsOn": [
				"[concat(variables('factoryId'), '/integrationRuntimes/integrationRuntime1')]"
			]
		},
		{
			"name": "[concat(parameters('factoryName'), '/LS_SQLSERVER')]",
			"type": "Microsoft.DataFactory/factories/linkedServices",
			"apiVersion": "2018-06-01",
			"properties": {
				"annotations": [],
				"type": "SqlServer",
				"typeProperties": {
					"server": "[parameters('LS_SQLSERVER_properties_typeProperties_server')]",
					"database": "[parameters('LS_SQLSERVER_properties_typeProperties_database')]",
					"encrypt": "optional",
					"trustServerCertificate": false,
					"authenticationType": "SQL",
					"userName": "[parameters('LS_SQLSERVER_properties_typeProperties_userName')]",
					"password": {
						"type": "SecureString",
						"value": "[parameters('LS_SQLSERVER_password')]"
					}
				},
				"connectVia": {
					"referenceName": "integrationRuntime1",
					"type": "IntegrationRuntimeReference"
				}
			},
			"dependsOn": [
				"[concat(variables('factoryId'), '/integrationRuntimes/integrationRuntime1')]"
			]
		},
		{
			"name": "[concat(parameters('factoryName'), '/LS_SQLSERVER_TABLE')]",
			"type": "Microsoft.DataFactory/factories/linkedServices",
			"apiVersion": "2018-06-01",
			"properties": {
				"annotations": [],
				"type": "SqlServer",
				"typeProperties": {
					"server": "[parameters('LS_SQLSERVER_TABLE_properties_typeProperties_server')]",
					"database": "[parameters('LS_SQLSERVER_TABLE_properties_typeProperties_database')]",
					"encrypt": "optional",
					"trustServerCertificate": false,
					"authenticationType": "SQL",
					"userName": "[parameters('LS_SQLSERVER_TABLE_properties_typeProperties_userName')]",
					"password": {
						"type": "SecureString",
						"value": "[parameters('LS_SQLSERVER_TABLE_password')]"
					}
				},
				"connectVia": {
					"referenceName": "integrationRuntime1",
					"type": "IntegrationRuntimeReference"
				}
			},
			"dependsOn": [
				"[concat(variables('factoryId'), '/integrationRuntimes/integrationRuntime1')]"
			]
		},
		{
			"name": "[concat(parameters('factoryName'), '/LS_SQLSER_TABLE')]",
			"type": "Microsoft.DataFactory/factories/linkedServices",
			"apiVersion": "2018-06-01",
			"properties": {
				"annotations": [],
				"type": "SqlServer",
				"typeProperties": {
					"server": "[parameters('LS_SQLSER_TABLE_properties_typeProperties_server')]",
					"database": "[parameters('LS_SQLSER_TABLE_properties_typeProperties_database')]",
					"encrypt": "optional",
					"trustServerCertificate": false,
					"authenticationType": "SQL",
					"userName": "[parameters('LS_SQLSER_TABLE_properties_typeProperties_userName')]",
					"password": {
						"type": "SecureString",
						"value": "[parameters('LS_SQLSER_TABLE_password')]"
					}
				},
				"connectVia": {
					"referenceName": "integrationRuntime1",
					"type": "IntegrationRuntimeReference"
				}
			},
			"dependsOn": [
				"[concat(variables('factoryId'), '/integrationRuntimes/integrationRuntime1')]"
			]
		},
		{
			"name": "[concat(parameters('factoryName'), '/LS_parquet')]",
			"type": "Microsoft.DataFactory/factories/linkedServices",
			"apiVersion": "2018-06-01",
			"properties": {
				"annotations": [],
				"type": "AzureBlobFS",
				"typeProperties": {
					"url": "[parameters('LS_parquet_properties_typeProperties_url')]",
					"accountKey": {
						"type": "SecureString",
						"value": "[parameters('LS_parquet_accountKey')]"
					}
				}
			},
			"dependsOn": []
		},
		{
			"name": "[concat(parameters('factoryName'), '/integrationRuntime1')]",
			"type": "Microsoft.DataFactory/factories/integrationRuntimes",
			"apiVersion": "2018-06-01",
			"properties": {
				"type": "SelfHosted",
				"typeProperties": {}
			},
			"dependsOn": []
		}
	]
}